autobib/__init__.py
autobib/_version.py
autobib/util.py
autobib-0.8.1.dist-info/LICENSE
autobib-0.8.1.dist-info/METADATA
autobib-0.8.1.dist-info/WHEEL
autobib-0.8.1.dist-info/entry_points.txt
autobib-0.8.1.dist-info/top_level.txt
autobib-0.8.1.dist-info/RECORD
