Metadata-Version: 2.1
Name: autobib
Version: 0.8.1
Summary: Automatically download missing entries to your bibliography file.
Home-page: https://github.com/hdembinski/autobib
Author: Hans Dembinski
Author-email: hans.dembinski@gmail.com
Project-URL: Bug Tracker, https://github.com/hdembinski/autobib/issues
Classifier: Programming Language :: Python :: 3
Classifier: License :: OSI Approved :: MIT License
Classifier: Operating System :: OS Independent
Classifier: Development Status :: 4 - Beta
Classifier: Environment :: Console
Classifier: Environment :: MacOS X
Classifier: Operating System :: MacOS
Classifier: Operating System :: POSIX
Classifier: Operating System :: Unix
Classifier: Topic :: Scientific/Engineering
Classifier: Topic :: Text Processing :: Markup :: LaTeX
Requires-Python: >=3.7
License-File: LICENSE
Provides-Extra: test
Requires-Dist: pytest ; extra == 'test'
Requires-Dist: pre-commit ; extra == 'test'
Requires-Dist: types-setuptools ; extra == 'test'
